jquants_pairs_trading/__init__.py
jquants_pairs_trading/jquants_pairs_trading.py
jquants_pairs_trading-0.1.2.dist-info/LICENCE.txt
jquants_pairs_trading-0.1.2.dist-info/METADATA
jquants_pairs_trading-0.1.2.dist-info/WHEEL
jquants_pairs_trading-0.1.2.dist-info/top_level.txt
jquants_pairs_trading-0.1.2.dist-info/RECORD
