Metadata-Version: 2.1
Name: jquants-pairs-trading
Version: 0.1.2
Summary: jquants-pairs-trading is a python library for backtest with japanese stock pairs trading using kalman filter, J-Quants on Python 3.8 and above.
Author-email: 10mohi6 <10.mohi.6.y@gmail.com>
Project-URL: Homepage, https://github.com/10mohi6/jquants-pairs-trading-python
Project-URL: Documentation, https://github.com/10mohi6/jquants-pairs-trading-python
Project-URL: Repository, https://github.com/10mohi6/jquants-pairs-trading-python.git
Keywords: pairs trading,backtest,kalman filter,python,japanese stock,J-Quants,jquants
Classifier: Development Status :: 4 - Beta
Classifier: Programming Language :: Python
Classifier: Programming Language :: Python :: 3
Classifier: Programming Language :: Python :: 3.8
Classifier: Programming Language :: Python :: 3.9
Classifier: Programming Language :: Python :: 3.10
Classifier: Programming Language :: Python :: 3.11
Classifier: Intended Audience :: Developers
Classifier: Intended Audience :: Financial and Insurance Industry
Classifier: Operating System :: OS Independent
Classifier: Topic :: Office/Business :: Financial :: Investment
Classifier: License :: OSI Approved :: MIT License
Requires-Python: >=3.8
License-File: LICENCE.txt
Requires-Dist: jquants-api-client
Requires-Dist: pykalman-bardo
Requires-Dist: statsmodels
Requires-Dist: pandas
Requires-Dist: matplotlib
Requires-Dist: seaborn
Provides-Extra: dev
Requires-Dist: pytest ; extra == 'dev'
Requires-Dist: pytest-cov ; extra == 'dev'
Requires-Dist: pytest-mock ; extra == 'dev'
